odoo/addons/crm_meeting_commercial_partner/README.rst
odoo/addons/crm_meeting_commercial_partner/__init__.py
odoo/addons/crm_meeting_commercial_partner/__manifest__.py
odoo/addons/crm_meeting_commercial_partner/i18n/crm_meeting_commercial_partner.pot
odoo/addons/crm_meeting_commercial_partner/models/__init__.py
odoo/addons/crm_meeting_commercial_partner/models/res_partner.py
odoo/addons/crm_meeting_commercial_partner/readme/CONTRIBUTORS.rst
odoo/addons/crm_meeting_commercial_partner/readme/DESCRIPTION.rst
odoo/addons/crm_meeting_commercial_partner/readme/USAGE.rst
odoo/addons/crm_meeting_commercial_partner/static/description/icon.png
odoo/addons/crm_meeting_commercial_partner/static/description/index.html
odoo/addons/crm_meeting_commercial_partner/tests/__init__.py
odoo/addons/crm_meeting_commercial_partner/tests/test_crm_meeting_commercial_partner.py
odoo13_addon_crm_meeting_commercial_partner-13.0.1.0.1.dist-info/METADATA
odoo13_addon_crm_meeting_commercial_partner-13.0.1.0.1.dist-info/WHEEL
odoo13_addon_crm_meeting_commercial_partner-13.0.1.0.1.dist-info/top_level.txt
odoo13_addon_crm_meeting_commercial_partner-13.0.1.0.1.dist-info/RECORD
